logtools_vrb/__init__.py
logtools_vrb/__version__.py
logtools_vrb/formatting.py
logtools_vrb/logtools.py
logtools_vrb/mailloghandler.py
logtools_vrb/py.typed
logtools_vrb-0.8.0.dist-info/METADATA
logtools_vrb-0.8.0.dist-info/WHEEL
logtools_vrb-0.8.0.dist-info/licenses/LICENSE
logtools_vrb-0.8.0.dist-info/RECORD
