Metadata-Version: 2.3
Name: logtools_vrb
Version: 0.8.0
Summary: Logging tools
Project-URL: Homepage, https://github.com/v-r-b/logtools_vrb
Project-URL: Issues, https://github.com/v-r-b/logtools_vrb/issues
Author-email: volker <volker@vrbdev.eu>
Maintainer-email: volker <volker@vrbdev.eu>
License-File: LICENSE
Classifier: Development Status :: 4 - Beta
Classifier: Intended Audience :: Developers
Classifier: License :: OSI Approved :: GNU General Public License v3 (GPLv3)
Classifier: Operating System :: OS Independent
Classifier: Programming Language :: Python :: 3
Classifier: Topic :: Software Development :: Libraries :: Python Modules
Requires-Python: >=3.9
Requires-Dist: mailtools-vrb
